taxmistri/__init__.py
taxmistri/capital_gains.py
taxmistri/income_tax.py
taxmistri-0.1.2.dist-info/licenses/LICENSE
taxmistri-0.1.2.dist-info/METADATA
taxmistri-0.1.2.dist-info/WHEEL
taxmistri-0.1.2.dist-info/top_level.txt
taxmistri-0.1.2.dist-info/RECORD
