Metadata-Version: 2.4
Name: taxmistri
Version: 0.1.2
Summary: TaxMistri simplifies Indian Tax calculations using Python.
Home-page: https://github.com/debjitl45/Tax-Mistri
Author: Debjit Karmakar
Author-email: Debjit Karmakar <karmadebjit@gmail.com>
License: MIT
Project-URL: Homepage, https://github.com/debjitl45/Tax-Mistri
Requires-Python: >=3.7
License-File: LICENSE
Dynamic: author
Dynamic: home-page
Dynamic: license-file
Dynamic: requires-python
